flygame/__init__.py
flygame/color.py
flygame/constants.py
flygame/event.py
flygame/font.py
flygame/grid.py
flygame/hitbox.py
flygame/image.py
flygame/mouse.py
flygame/object.py
flygame/position.py
flygame/render_context.py
flygame/window.py
flygame-0.1.4.dist-info/LICENSE
flygame-0.1.4.dist-info/METADATA
flygame-0.1.4.dist-info/WHEEL
flygame-0.1.4.dist-info/top_level.txt
flygame-0.1.4.dist-info/RECORD
