Metadata-Version: 2.1
Name: flygame
Version: 0.1.4
Summary: A Private Project so i can render stuff more easily
Author-email: fluffy <fluffykms@gmail.com>
Classifier: Programming Language :: Python :: 3
Classifier: License :: OSI Approved :: MIT License
Classifier: Operating System :: OS Independent
Requires-Python: >=3.8
License-File: LICENSE
